<library path="src">
  <class name="Teleop" type="concert_qt_teleop.teleop.Teleop" base_class_type="rqt_gui_py::Plugin">
    <description>
        Select and teleop a robot in the concert.
    </description>
    <qtgui>
      <group>
        <label>Concert</label>
        <icon type="theme">folder</icon>
        <statustip>Concert plugins for ROCON.</statustip>
      </group>
      <label>Teleop</label>
      <icon type="file">./resources/images/rocon_logo.png</icon>
      <statustip>Select and teleop a robot in the concert.</statustip>
    </qtgui>
  </class>
</library>
